{
  "symbol": "BBSE3",
  "shortName": "BBSE3",
  "longName": "BB Seguridade Participacoes SA",
  "currency": "BRL",
  "regularMarketPrice": 35.05,
  "regularMarketDayHigh": 35.62,
  "regularMarketDayLow": 34.88,
  "regularMarketDayRange": "34.88 - 35.62",
  "regularMarketChange": -0.68,
  "regularMarketChangePercent": -1.9,
  "regularMarketTime": "2026-04-15T15:54:48.000Z",
  "marketCap": 69247831468,
  "regularMarketVolume": 3431200,
  "regularMarketPreviousClose": 35.05,
  "regularMarketOpen": 35.62,
  "fiftyTwoWeekRange": "31.53 - 42.77",
  "fiftyTwoWeekLow": 31.53,
  "fiftyTwoWeekHigh": 42.77,
  "priceEarnings": 7.545423232584172,
  "earningsPerShare": 4.6452085,
  "logourl": "https://icons.brapi.dev/icons/BBSE3.svg",
  "usedInterval": "1d",
  "usedRange": "3mo",
  "historicalDataPrice": [],
  "validRanges": [
    "1d",
    "2d",
    "5d",
    "7d",
    "1mo",
    "3mo",
    "6mo",
    "1y",
    "2y",
    "5y",
    "10y",
    "ytd",
    "max"
  ],
  "validIntervals": [
    "1m",
    "2m",
    "5m",
    "15m",
    "30m",
    "60m",
    "90m",
    "1h",
    "1d",
    "5d",
    "1wk",
    "1mo",
    "3mo"
  ]
}